[
  {
    "title": "virtuoso",
    "github_url": "https://github.com/rpmessner/virtuoso",
    "author": "rpmessner",
    "description":
      "Translate chord names to finger positions on a guitar fretboard\n",
    "screenshot_url": "images/virtuoso.png",
    "hrcpt_url": "https://rpmessner.github.io",
    "author_url": "http://github.com/"
  },
  {
    "title": "shapedrawer",
    "github_url": "https://github.com/chriserin/ShapeDrawer",
    "author": "chriserin",
    "description":
      "This started out as an experiment to create fonts+typography out of html+css shapes.  Whether or not that was achieved is up for judgement, it was fun though.  It is an extensive single page backbone.js + coffeescript application written when those technologies received a big boost by the introduction of the asset pipeline in Rails.\n",
    "screenshot_url": "images/shapedrawer.png",
    "hrcpt_url": "https://shapedrawer.herokuapp.com",
    "author_url": "http://github.com/"
  },
  {
    "title": "triangles",
    "github_url": "https://github.com/chriserin/triangles",
    "author": "chriserin",
    "description": "A place to play with triangles\n",
    "screenshot_url": "images/triangles.png",
    "hrcpt_url": "https://chris-triangles.herokuapp.com",
    "author_url": "http://github.com/"
  },
  {
    "title": "squares-in-squares",
    "github_url": "https://github.com/chriserin/squares-in-squares",
    "author": "chriserin",
    "description": "A tool to create unique patterns with different shapes\n",
    "screenshot_url": "images/squares-in-squares.png",
    "hrcpt_url": "https://squares-in-squares.herokuapp.com",
    "author_url": "http://github.com/"
  },
  {
    "title": "ceramic-nation",
    "github_url": "https://github.com/jwworth/novel",
    "author": "jwworth",
    "description":
      "Ceramic Nation is an autogenerated novel that generates a chapter a day through Markovian means.\n",
    "screenshot_url": "images/ceramic-nation.png",
    "hrcpt_url": "https://novel.herokuapp.com",
    "author_url": "http://github.com/"
  },
  {
    "title": "elmlife",
    "github_url": "https://github.com/briandunn/elmlife",
    "author": "briandunn",
    "description": "Conway's Game of Life, in Elm",
    "screenshot_url": "images/elmlife.png",
    "hrcpt_url": "https://briandunn.github.io/elmlife/",
    "author_url": "http://github.com/"
  },
  {
    "title": "versions",
    "github_url": "https://github.com/chriserin/stack_versions",
    "author": "chriserin",
    "description": "A timeline for software\n",
    "screenshot_url": "images/versions.png",
    "hrcpt_url": "https://software-versions-ui.herokuapp.com",
    "author_url": "http://github.com/"
  },
  {
    "title": "elmlife",
    "github_url": "https://github.com/chriserin/elmlife",
    "author": "chriserin",
    "description": "Conway's Game of Life, in Elm",
    "screenshot_url": "images/elmlife.png",
    "hrcpt_url": "https://briandunn.github.io/elmlife/index.html",
    "author_url": "http://github.com/"
  },
  {
    "title": "conway-react",
    "github_url": "https://github.com/jwworth/conway",
    "author": "jwworth",
    "description": "This is Conway's Game of Life in React.js.\n",
    "screenshot_url": "images/conway-react.png",
    "hrcpt_url": "https://conway-react.herokuapp.com/",
    "author_url": "http://github.com/"
  }
]
